supertunnel/__init__.py
supertunnel/command.py
supertunnel/command_test.py
supertunnel/conftest.py
supertunnel/jupyter.py
supertunnel/jupyter_test.py
supertunnel/log.py
supertunnel/messaging.py
supertunnel/messaging_test.py
supertunnel/port.py
supertunnel/port_test.py
supertunnel/ssh/__init__.py
supertunnel/ssh/config.py
supertunnel/ssh/config_test.py
supertunnel/ssh/continuous.py
supertunnel/ssh/continuous_test.py
supertunnel/ssh/helpers.py
supertunnel-0.1.dist-info/LICENSE
supertunnel-0.1.dist-info/METADATA
supertunnel-0.1.dist-info/WHEEL
supertunnel-0.1.dist-info/entry_points.txt
supertunnel-0.1.dist-info/top_level.txt
supertunnel-0.1.dist-info/RECORD
