Metadata-Version: 2.1
Name: supertunnel
Version: 0.1
Summary: SuperTunnel makes for easy, long-lived SSH tunneling!
Home-page: https://github.com/alexrudy/supertunnel
Author: Alex Rudy
Author-email: alex.rudy@gmail.com
License: UNKNOWN
Keywords: utilties ssh networking
Platform: UNKNOWN
Classifier: Development Status :: 3 - Alpha
Classifier: Intended Audience :: Developers
Classifier: Environment :: Console
Classifier: License :: OSI Approved :: BSD License
Classifier: Operating System :: Unix
Classifier: Programming Language :: Python :: 3.6
Classifier: Programming Language :: Python :: 3.7
Classifier: Programming Language :: Python :: 3 :: Only
Classifier: Topic :: Utilities
Requires-Python: >=3.6, <4
Requires-Dist: click
Requires-Dist: dataclasses ; python_version < "3.7"
